Metadata-Version: 2.1
Name: markmoji
Version: 1.2
Summary: Extends the basic markdown syntax using an easy to understand and quickly readable emoji-based syntax.
Home-page: https://TEParsons.github.io/Markmoji
Download-URL: https://github.com/TEParsons/Markmoji/archive/refs/tags/v1.2.tar.gz
Author: Todd Parsons
Author-email: todd.e.parsons@gmail.com
Maintainer-email: todd.e.parsons@gmail.com
Classifier: Development Status :: 4 - Beta
Classifier: Operating System :: MacOS :: MacOS X
Classifier: Operating System :: Microsoft :: Windows
Classifier: Operating System :: POSIX :: Linux
Classifier: Programming Language :: Python :: 3
Classifier: Programming Language :: Python :: 3.6
Classifier: Programming Language :: Python :: 3.7
Classifier: Programming Language :: Python :: 3.8
Classifier: Programming Language :: Python :: 3.9
Classifier: Programming Language :: Python :: 3.10
Requires-Python: >=3.6
Provides-Extra: suggested
